torsel/__init__.py
torsel/cookies_manager.py
torsel/torsel.py
torsel-0.4.31.dist-info/LICENSE
torsel-0.4.31.dist-info/METADATA
torsel-0.4.31.dist-info/WHEEL
torsel-0.4.31.dist-info/top_level.txt
torsel-0.4.31.dist-info/RECORD
