Metadata-Version: 2.1
Name: torsel
Version: 0.4.31
Summary: A Python module for managing Tor instances with Selenium
Home-page: https://github.com/azuk4r/torsel
Author: azuk4r
Author-email: azuk4r@tuta.io
Keywords: tor selenium web scraping automation
Classifier: Programming Language :: Python :: 3
Classifier: Operating System :: POSIX :: Linux
Classifier: Operating System :: Microsoft :: Windows
Classifier: Operating System :: MacOS
Classifier: License :: OSI Approved :: MIT License
Requires-Python: >=3.8
License-File: LICENSE
Requires-Dist: selenium
Requires-Dist: stem
